LICENSE
MANIFEST.in
README
setup.py
Flask_Breve.egg-info/PKG-INFO
Flask_Breve.egg-info/SOURCES.txt
Flask_Breve.egg-info/dependency_links.txt
Flask_Breve.egg-info/namespace_packages.txt
Flask_Breve.egg-info/not-zip-safe
Flask_Breve.egg-info/requires.txt
Flask_Breve.egg-info/top_level.txt
flaskext/__init__.py
flaskext/breve.py