Metadata-Version: 1.0
Name: Flask-Breve
Version: 0.2
Summary: Breve templating with Flask
Home-page: http://github.com/dgerber/Flask-Breve
Author: Daniel Gerber
Author-email: daniel.g.gerber@gmail.com
License: BSD
Platform: any
Classifier: Development Status :: 4 - Beta
Classifier: Environment :: Web Environment
Classifier: Intended Audience :: Developers
Classifier: License :: OSI Approved :: BSD License
Classifier: Operating System :: OS Independent
Classifier: Programming Language :: Python
Classifier: Topic :: Internet :: WWW/HTTP :: Dynamic Content
Classifier: Topic :: Software Development :: Libraries :: Python Modules
